pydbms/__init__.py
codedb-0.0.1.dist-info/License.txt
codedb-0.0.1.dist-info/METADATA
codedb-0.0.1.dist-info/WHEEL
codedb-0.0.1.dist-info/top_level.txt
codedb-0.0.1.dist-info/RECORD
