Metadata-Version: 2.1
Name: codedb
Version: 0.0.1
Summary: A small package on DBMS College Project
Author: Sikandar Bhide
License: UNKNOWN
Platform: UNKNOWN
Requires-Python: >=3.6
License-File: License.txt
